ebisu/__init__.py
ebisu/alternate.py
ebisu/ebisu.py
ebisu-2.2.0.dist-info/METADATA
ebisu-2.2.0.dist-info/WHEEL
ebisu-2.2.0.dist-info/top_level.txt
ebisu-2.2.0.dist-info/zip-safe
ebisu-2.2.0.dist-info/RECORD
