Metadata-Version: 2.1
Name: ebisu
Version: 2.2.0
Summary: Intelligent quiz scheduling
Home-page: http://github.com/fasiha/ebisu
Author: Ahmed Fasih
Author-email: wuzzyview@gmail.com
License: Unlicense
Keywords: quiz review schedule spaced repetition system srs bayesian probability beta random variable
Requires-Dist: scipy
Requires-Dist: numpy
